{"doc_key": "news-train-1", "sentence": ["EU", "rejects", "German", "call", "to", "boycott", "British", "lamb", "."], "ner": [[0, 0, "organisation"], [2, 3, "misc"], [6, 7, "misc"]], "relations": [[0, 0, 2, 3, "opposite", "rejects", false, false], [2, 3, 6, 7, "opposite", "calls_for_boycot_of", false, false], [2, 3, 6, 7, "topic", "", false, false]]}
{"doc_key": "news-train-2", "sentence": ["Peter", "Blackburn"], "ner": [[0, 1, "person"]], "relations": []}
{"doc_key": "news-train-3", "sentence": ["BRUSSELS", "1996-08-22"], "ner": [[0, 0, "location"]], "relations": []}
{"doc_key": "news-train-4", "sentence": ["The", "European", "Commission", "said", "on", "Thursday", "it", "disagreed", "with", "German", "advice", "to", "consumers", "to", "shun", "British", "lamb", "until", "scientists", "determine", "whether", "mad", "cow", "disease", "can", "be", "transmitted", "to", "sheep", "."], "ner": [[1, 2, "organisation"], [9, 10, "misc"], [15, 16, "misc"]], "relations": [[1, 2, 9, 10, "opposite", "rejects", false, false], [9, 10, 15, 16, "opposite", "calls_for_boycot_of", false, false], [9, 10, 15, 16, "topic", "", false, false]]}
{"doc_key": "news-train-5", "sentence": ["Germany", "'s", "representative", "to", "the", "European", "Union", "'s", "veterinary", "committee", "Werner", "Zwingmann", "said", "on", "Wednesday", "consumers", "should", "buy", "sheepmeat", "from", "countries", "other", "than", "Britain", "until", "the", "scientific", "advice", "was", "clearer", "."], "ner": [[0, 0, "country"], [5, 6, "organisation"], [10, 11, "person"], [23, 23, "location"]], "relations": [[0, 0, 5, 6, "part-of", "", false, false], [10, 11, 0, 0, "role", "representative_for", false, false], [10, 11, 5, 6, "role", "works_in", false, false], [10, 11, 23, 23, "opposite", "discourages_trade_with", false, false]]}
{"doc_key": "news-train-6", "sentence": ["\"", "We", "do", "n't", "support", "any", "such", "recommendation", "because", "we", "do", "n't", "see", "any", "grounds", "for", "it", ",", "\"", "the", "Commission", "'s", "chief", "spokesman", "Nikolaus", "van", "der", "Pas", "told", "a", "news", "briefing", "."], "ner": [[20, 20, "organisation"], [24, 27, "person"]], "relations": [[24, 27, 20, 20, "role", "spokesman_for", false, false]]}
{"doc_key": "news-train-7", "sentence": ["He", "said", "further", "scientific", "study", "was", "required", "and", "if", "it", "was", "found", "that", "action", "was", "needed", "it", "should", "be", "taken", "by", "the", "European", "Union", "."], "ner": [[22, 23, "organisation"]], "relations": []}
{"doc_key": "news-train-8", "sentence": ["He", "said", "a", "proposal", "last", "month", "by", "EU", "Farm", "Commissioner", "Franz", "Fischler", "to", "ban", "sheep", "brains", ",", "spleens", "and", "spinal", "cords", "from", "the", "human", "and", "animal", "food", "chains", "was", "a", "highly", "specific", "and", "precautionary", "move", "to", "protect", "human", "health", "."], "ner": [[7, 7, "organisation"], [10, 11, "person"]], "relations": [[10, 11, 7, 7, "role", "", false, false]]}
{"doc_key": "news-train-9", "sentence": ["Fischler", "proposed", "EU-wide", "measures", "after", "reports", "from", "Britain", "and", "France", "that", "under", "laboratory", "conditions", "sheep", "could", "contract", "Bovine", "Spongiform", "Encephalopathy", "(", "BSE", ")", "--", "mad", "cow", "disease", "."], "ner": [[0, 0, "person"], [2, 3, "misc"], [7, 7, "location"], [9, 9, "location"], [17, 19, "misc"], [21, 21, "misc"]], "relations": [[2, 3, 0, 0, "origin", "proposed_by", false, false], [21, 21, 17, 19, "named", "", false, false]]}
{"doc_key": "news-train-10", "sentence": ["But", "Fischler", "agreed", "to", "review", "his", "proposal", "after", "the", "EU", "'s", "standing", "veterinary", "committee", ",", "mational", "animal", "health", "officials", ",", "questioned", "if", "such", "action", "was", "justified", "as", "there", "was", "only", "a", "slight", "risk", "to", "human", "health", "."], "ner": [[1, 1, "person"], [9, 9, "organisation"]], "relations": []}
{"doc_key": "news-train-11", "sentence": ["Spanish", "Farm", "Minister", "Loyola", "de", "Palacio", "had", "earlier", "accused", "Fischler", "at", "an", "EU", "farm", "ministers", "'", "meeting", "of", "causing", "unjustified", "alarm", "through", "\"", "dangerous", "generalisation", ".", "\""], "ner": [[0, 2, "misc"], [3, 5, "person"], [9, 9, "person"], [12, 12, "organisation"]], "relations": [[0, 2, 3, 5, "named", "", false, false], [3, 5, 9, 9, "opposite", "", false, false], [3, 5, 12, 12, "role", "", false, false], [9, 9, 12, 12, "role", "", false, false]]}
{"doc_key": "news-train-12", "sentence": ["."], "ner": [], "relations": []}
{"doc_key": "news-train-13", "sentence": ["Only", "France", "and", "Britain", "backed", "Fischler", "'s", "proposal", "."], "ner": [[1, 1, "location"], [3, 3, "location"], [5, 5, "person"]], "relations": [[1, 1, 3, 3, "role", "backs_proposal_of", false, false], [1, 1, 5, 5, "role", "backs_proposal_of", false, false]]}
{"doc_key": "news-train-14", "sentence": ["The", "EU", "'s", "scientific", "veterinary", "and", "multidisciplinary", "committees", "are", "due", "to", "re-examine", "the", "issue", "early", "next", "month", "and", "make", "recommendations", "to", "the", "senior", "veterinary", "officials", "."], "ner": [[1, 1, "organisation"]], "relations": []}
{"doc_key": "news-train-15", "sentence": ["Sheep", "have", "long", "been", "known", "to", "contract", "scrapie", ",", "a", "brain-wasting", "disease", "similar", "to", "BSE", "which", "is", "believed", "to", "have", "been", "transferred", "to", "cattle", "through", "feed", "containing", "animal", "waste", "."], "ner": [[14, 14, "misc"]], "relations": []}
{"doc_key": "news-train-16", "sentence": ["British", "farmers", "denied", "on", "Thursday", "there", "was", "any", "danger", "to", "human", "health", "from", "their", "sheep", ",", "but", "expressed", "concern", "that", "German", "government", "advice", "to", "consumers", "to", "avoid", "British", "lamb", "might", "influence", "consumers", "across", "Europe", "."], "ner": [[0, 1, "misc"], [20, 22, "misc"], [27, 28, "misc"], [33, 33, "location"]], "relations": [[0, 1, 20, 22, "opposite", "", false, false], [20, 22, 27, 28, "opposite", "dissuades_customers_from", false, false]]}
{"doc_key": "news-train-17", "sentence": ["\"", "What", "we", "have", "to", "be", "extremely", "careful", "of", "is", "how", "other", "countries", "are", "going", "to", "take", "Germany", "'s", "lead", ",", "\"", "Welsh", "National", "Farmers", "'", "Union", "(", "NFU", ")", "chairman", "John", "Lloyd", "Jones", "said", "on", "BBC", "radio", "."], "ner": [[17, 17, "country"], [22, 26, "organisation"], [28, 28, "organisation"], [31, 33, "person"], [36, 37, "organisation"]], "relations": [[28, 28, 22, 26, "named", "", false, false], [31, 33, 22, 26, "role", "", false, false], [31, 33, 36, 37, "usage", "", false, false]]}
{"doc_key": "news-train-18", "sentence": ["Bonn", "has", "led", "efforts", "to", "protect", "public", "health", "after", "consumer", "confidence", "collapsed", "in", "March", "after", "a", "British", "report", "suggested", "humans", "could", "contract", "an", "illness", "similar", "to", "mad", "cow", "disease", "by", "eating", "contaminated", "beef", "."], "ner": [[0, 0, "location"], [16, 17, "misc"]], "relations": []}
{"doc_key": "news-train-19", "sentence": ["Germany", "imported", "47,600", "sheep", "from", "Britain", "last", "year", ",", "nearly", "half", "of", "total", "imports", "."], "ner": [[0, 0, "country"], [5, 5, "location"]], "relations": [[0, 0, 5, 5, "role", "import_goods_from", false, false]]}
{"doc_key": "news-train-20", "sentence": ["It", "brought", "in", "4,275", "tonnes", "of", "British", "mutton", ",", "some", "10", "percent", "of", "overall", "imports", "."], "ner": [[6, 7, "misc"]], "relations": []}
{"doc_key": "news-train-21", "sentence": ["Rare", "Hendrix", "song", "draft", "sells", "for", "almost", "$", "17,000", "."], "ner": [[1, 1, "person"]], "relations": []}
{"doc_key": "news-train-22", "sentence": ["LONDON", "1996-08-22"], "ner": [[0, 0, "location"]], "relations": []}
{"doc_key": "news-train-23", "sentence": ["A", "rare", "early", "handwritten", "draft", "of", "a", "song", "by", "U.S.", "guitar", "legend", "Jimi", "Hendrix", "was", "sold", "for", "almost", "$", "17,000", "on", "Thursday", "at", "an", "auction", "of", "some", "of", "the", "late", "musician", "'s", "favourite", "possessions", "."], "ner": [[9, 11, "misc"], [12, 13, "person"]], "relations": [[9, 11, 12, 13, "named", "", false, false]]}
{"doc_key": "news-train-24", "sentence": ["A", "Florida", "restaurant", "paid", "10,925", "pounds", "(", "$", "16,935", ")", "for", "the", "draft", "of", "\"", "Ai", "n't", "no", "telling", "\"", ",", "which", "Hendrix", "penned", "on", "a", "piece", "of", "London", "hotel", "stationery", "in", "late", "1966", "."], "ner": [[1, 1, "location"], [15, 18, "misc"], [22, 22, "person"], [28, 28, "location"]], "relations": [[1, 1, 15, 18, "related-to", "purchases", false, false], [15, 18, 22, 22, "artifact", "", false, false], [22, 22, 28, 28, "physical", "", false, false]]}
{"doc_key": "news-train-25", "sentence": ["At", "the", "end", "of", "a", "January", "1967", "concert", "in", "the", "English", "city", "of", "Nottingham", "he", "threw", "the", "sheet", "of", "paper", "into", "the", "audience", ",", "where", "it", "was", "retrieved", "by", "a", "fan", "."], "ner": [[10, 11, "misc"], [13, 13, "location"]], "relations": [[13, 13, 10, 11, "general-affiliation", "", false, false]]}
{"doc_key": "news-train-26", "sentence": ["Buyers", "also", "snapped", "up", "16", "other", "items", "that", "were", "put", "up", "for", "auction", "by", "Hendrix", "'s", "former", "girlfriend", "Kathy", "Etchingham", ",", "who", "lived", "with", "him", "from", "1966", "to", "1969", "."], "ner": [[14, 14, "person"], [18, 19, "person"]], "relations": [[14, 14, 18, 19, "social", "", false, false]]}
{"doc_key": "news-train-27", "sentence": ["They", "included", "a", "black", "lacquer", "and", "mother", "of", "pearl", "inlaid", "box", "used", "by", "Hendrix", "to", "store", "his", "drugs", ",", "which", "an", "anonymous", "Australian", "purchaser", "bought", "for", "5,060", "pounds", "(", "$", "7,845", ")", "."], "ner": [[13, 13, "person"], [22, 23, "misc"]], "relations": []}
{"doc_key": "news-train-28", "sentence": ["The", "guitarist", "died", "of", "a", "drugs", "overdose", "in", "1970", "aged", "27", "."], "ner": [], "relations": []}
{"doc_key": "news-train-29", "sentence": ["China", "says", "Taiwan", "spoils", "atmosphere", "for", "talks", "."], "ner": [[0, 0, "location"], [2, 2, "location"]], "relations": [[0, 0, 2, 2, "opposite", "", false, false]]}
{"doc_key": "news-train-30", "sentence": ["BEIJING", "1996-08-22"], "ner": [[0, 0, "location"]], "relations": []}
{"doc_key": "news-train-31", "sentence": ["China", "on", "Thursday", "accused", "Taipei", "of", "spoiling", "the", "atmosphere", "for", "a", "resumption", "of", "talks", "across", "the", "Taiwan", "Strait", "with", "a", "visit", "to", "Ukraine", "by", "Taiwanese", "Vice", "President", "Lien", "Chan", "this", "week", "that", "infuriated", "Beijing", "."], "ner": [[0, 0, "country"], [4, 4, "location"], [16, 17, "location"], [22, 22, "country"], [24, 26, "misc"], [27, 28, "person"], [33, 33, "location"]], "relations": [[0, 0, 4, 4, "opposite", "", false, false], [24, 26, 27, 28, "named", "", false, false], [27, 28, 22, 22, "physical", "visits", false, false], [27, 28, 33, 33, "opposite", "", false, false]]}
{"doc_key": "news-train-32", "sentence": ["Speaking", "only", "hours", "after", "Chinese", "state", "media", "said", "the", "time", "was", "right", "to", "engage", "in", "political", "talks", "with", "Taiwan", ",", "Foreign", "Ministry", "spokesman", "Shen", "Guofang", "told", "Reuters", ":", "\"", "The", "necessary", "atmosphere", "for", "the", "opening", "of", "the", "talks", "has", "been", "disrupted", "by", "the", "Taiwan", "authorities", ".", "\""], "ner": [[4, 6, "misc"], [18, 18, "location"], [20, 21, "organisation"], [23, 24, "person"], [26, 26, "organisation"], [43, 43, "location"]], "relations": [[18, 18, 43, 43, "named", "same", false, false], [23, 24, 20, 21, "role", "", false, false], [23, 24, 43, 43, "opposite", "", false, false]]}
{"doc_key": "news-train-33", "sentence": ["State", "media", "quoted", "China", "'s", "top", "negotiator", "with", "Taipei", ",", "Tang", "Shubei", ",", "as", "telling", "a", "visiting", "group", "from", "Taiwan", "on", "Wednesday", "that", "it", "was", "time", "for", "the", "rivals", "to", "hold", "political", "talks", "."], "ner": [[3, 3, "location"], [8, 8, "location"], [10, 11, "person"], [19, 19, "location"]], "relations": [[10, 11, 3, 3, "role", "negotiatior_for", false, false], [10, 11, 8, 8, "role", "negotiates_with", false, false]]}
{"doc_key": "news-train-34", "sentence": ["\"", "Now", "is", "the", "time", "for", "the", "two", "sides", "to", "engage", "in", "political", "talks", "..."], "ner": [], "relations": []}
{"doc_key": "news-train-35", "sentence": ["that", "is", "to", "end", "the", "state", "of", "hostility", ",", "\"", "Thursday", "'s", "overseas", "edition", "of", "the", "People", "'s", "Daily", "quoted", "Tang", "as", "saying", "."], "ner": [[16, 18, "organisation"], [20, 20, "person"]], "relations": [[16, 18, 20, 20, "related-to", "quotes", false, false]]}
{"doc_key": "news-train-36", "sentence": ["The", "foreign", "ministry", "'s", "Shen", "told", "Reuters", "Television", "in", "an", "interview", "he", "had", "read", "reports", "of", "Tang", "'s", "comments", "but", "gave", "no", "details", "of", "why", "the", "negotiator", "had", "considered", "the", "time", "right", "for", "talks", "with", "Taiwan", ",", "which", "Beijing", "considers", "a", "renegade", "province", "."], "ner": [[4, 4, "organisation"], [6, 7, "organisation"], [16, 16, "person"], [35, 35, "location"], [38, 38, "location"]], "relations": [[4, 4, 6, 7, "related-to", "relays_information_to", false, false], [35, 35, 38, 38, "opposite", "", false, false]]}
{"doc_key": "news-train-37", "sentence": ["China", ",", "which", "has", "long", "opposed", "all", "Taipei", "efforts", "to", "gain", "greater", "international", "recognition", ",", "was", "infuriated", "by", "a", "visit", "to", "Ukraine", "this", "week", "by", "Taiwanese", "Vice", "President", "Lien", "."], "ner": [[0, 0, "location"], [7, 7, "location"], [21, 21, "location"], [25, 27, "misc"], [28, 28, "person"]], "relations": [[0, 0, 7, 7, "opposite", "", false, false], [25, 27, 28, 28, "named", "", false, false], [28, 28, 21, 21, "physical", "visits", false, false], [28, 28, 21, 21, "role", "vice_president_of", false, false]]}
{"doc_key": "news-train-38", "sentence": ["China", "says", "time", "right", "for", "Taiwan", "talks", "."], "ner": [[0, 0, "location"], [5, 5, "location"]], "relations": [[0, 0, 5, 5, "role", "", false, false]]}
{"doc_key": "news-train-39", "sentence": ["BEIJING", "1996-08-22"], "ner": [[0, 0, "location"]], "relations": []}
{"doc_key": "news-train-40", "sentence": ["China", "has", "said", "it", "was", "time", "for", "political", "talks", "with", "Taiwan", "and", "that", "the", "rival", "island", "should", "take", "practical", "steps", "towards", "that", "goal", "."], "ner": [[0, 0, "location"], [10, 10, "location"]], "relations": [[0, 0, 10, 10, "role", "", false, false]]}
{"doc_key": "news-train-41", "sentence": ["Consultations", "should", "be", "held", "to", "set", "the", "time", "and", "format", "of", "the", "talks", ",", "the", "official", "Xinhua", "news", "agency", "quoted", "Tang", "Shubei", ",", "executive", "vice", "chairman", "of", "the", "Association", "for", "Relations", "Across", "the", "Taiwan", "Straits", ",", "as", "saying", "late", "on", "Wednesday", "."], "ner": [[16, 16, "organisation"], [20, 21, "person"], [28, 34, "organisation"]], "relations": [[16, 16, 20, 21, "related-to", "quotes", false, false], [20, 21, 28, 34, "role", "", false, false]]}
{"doc_key": "news-train-42", "sentence": ["German", "July", "car", "registrations", "up", "14.2", "pct", "yr", "/", "yr", "."], "ner": [[0, 0, "misc"]], "relations": []}
{"doc_key": "news-train-43", "sentence": ["FRANKFURT", "1996-08-22"], "ner": [[0, 0, "location"]], "relations": []}
{"doc_key": "news-train-44", "sentence": ["German", "first-time", "registrations", "of", "motor", "vehicles", "jumped", "14.2", "percent", "in", "July", "this", "year", "from", "the", "year-earlier", "period", ",", "the", "Federal", "office", "for", "motor", "vehicles", "said", "on", "Thursday", "."], "ner": [[0, 5, "misc"], [19, 23, "organisation"]], "relations": []}
{"doc_key": "news-train-45", "sentence": ["The", "office", "said", "356,725", "new", "cars", "were", "registered", "in", "July", "1996", "--", "304,850", "passenger", "cars", "and", "15,613", "trucks", "."], "ner": [], "relations": []}
{"doc_key": "news-train-46", "sentence": ["The", "figures", "represent", "a", "13.6", "percent", "increase", "for", "passenger", "cars", "and", "a", "2.2", "percent", "decline", "for", "trucks", "from", "July", "1995", "."], "ner": [], "relations": []}
{"doc_key": "news-train-47", "sentence": ["Motor-bike", "registration", "rose", "32.7", "percent", "in", "the", "period", "."], "ner": [], "relations": []}
{"doc_key": "news-train-48", "sentence": ["The", "growth", "was", "partly", "due", "to", "an", "increased", "number", "of", "Germans", "buying", "German", "cars", "abroad", ",", "while", "manufacturers", "said", "that", "domestic", "demand", "was", "weak", ",", "the", "federal", "office", "said", "."], "ner": [[10, 10, "misc"], [12, 13, "misc"]], "relations": [[10, 10, 12, 13, "related-to", "buys", false, false]]}
{"doc_key": "news-train-49", "sentence": ["Almost", "all", "German", "car", "manufacturers", "posted", "gains", "in", "registration", "numbers", "in", "the", "period", "."], "ner": [[2, 4, "misc"]], "relations": []}
{"doc_key": "news-train-50", "sentence": ["Volkswagen", "AG", "won", "77,719", "registrations", ",", "slightly", "more", "than", "a", "quarter", "of", "the", "total", "."], "ner": [[0, 1, "organisation"]], "relations": []}
{"doc_key": "news-train-51", "sentence": ["Opel", "AG", "together", "with", "General", "Motors", "came", "in", "second", "place", "with", "49,269", "registrations", ",", "16.4", "percent", "of", "the", "overall", "figure", "."], "ner": [[0, 1, "organisation"], [4, 5, "organisation"]], "relations": []}
{"doc_key": "news-train-52", "sentence": ["Third", "was", "Ford", "with", "35,563", "registrations", ",", "or", "11.7", "percent", "."], "ner": [[2, 2, "organisation"]], "relations": []}
{"doc_key": "news-train-53", "sentence": ["Only", "Seat", "and", "Porsche", "had", "fewer", "registrations", "in", "July", "1996", "compared", "to", "last", "year", "'s", "July", "."], "ner": [[1, 1, "organisation"], [3, 3, "organisation"]], "relations": []}
{"doc_key": "news-train-54", "sentence": ["Seat", "posted", "3,420", "registrations", "compared", "with", "5522", "registrations", "in", "July", "a", "year", "earlier", "."], "ner": [[0, 0, "organisation"]], "relations": []}
{"doc_key": "news-train-55", "sentence": ["Porsche", "'s", "registrations", "fell", "to", "554", "from", "643", "."], "ner": [[0, 0, "organisation"]], "relations": []}
{"doc_key": "news-train-56", "sentence": ["GREEK", "SOCIALISTS", "GIVE", "GREEN", "LIGHT", "TO", "PM", "FOR", "ELECTIONS", "."], "ner": [[0, 1, "misc"]], "relations": []}
{"doc_key": "news-train-57", "sentence": ["ATHENS", "1996-08-22"], "ner": [[0, 0, "location"]], "relations": []}
{"doc_key": "news-train-58", "sentence": ["The", "Greek", "socialist", "party", "'s", "executive", "bureau", "gave", "the", "green", "light", "to", "Prime", "Minister", "Costas", "Simitis", "to", "call", "snap", "elections", ",", "its", "general", "secretary", "Costas", "Skandalidis", "told", "reporters", "."], "ner": [[1, 3, "misc"], [14, 15, "person"], [24, 25, "person"]], "relations": [[1, 3, 14, 15, "role", "greenlight", false, false], [24, 25, 1, 3, "role", "", false, false]]}
{"doc_key": "news-train-59", "sentence": ["Prime", "Minister", "Costas", "Simitis", "is", "going", "to", "make", "an", "official", "announcement", "after", "a", "cabinet", "meeting", "later", "on", "Thursday", ",", "said", "Skandalidis", "."], "ner": [[2, 3, "person"], [20, 20, "person"]], "relations": []}
{"doc_key": "news-train-60", "sentence": ["--", "Dimitris", "Kontogiannis", ",", "Athens", "Newsroom", "+301", "3311812-4"], "ner": [[1, 2, "person"], [4, 5, "organisation"]], "relations": [[1, 2, 4, 5, "role", "", false, false]]}
{"doc_key": "news-train-61", "sentence": ["BayerVB", "sets", "C$", "100", "million", "six-year", "bond", "."], "ner": [[0, 0, "organisation"], [2, 2, "misc"]], "relations": []}
{"doc_key": "news-train-62", "sentence": ["LONDON", "1996-08-22"], "ner": [[0, 0, "location"]], "relations": []}
{"doc_key": "news-train-63", "sentence": ["The", "following", "bond", "was", "announced", "by", "lead", "manager", "Toronto", "Dominion", "."], "ner": [[8, 9, "person"]], "relations": []}
{"doc_key": "news-train-64", "sentence": ["BORROWER", "BAYERISCHE", "VEREINSBANK"], "ner": [[1, 2, "organisation"]], "relations": []}
{"doc_key": "news-train-65", "sentence": ["AMT", "C$", "100", "MLN", "COUPON", "6.625", "MATURITY", "24.SEP.02"], "ner": [[1, 1, "misc"]], "relations": []}
{"doc_key": "news-train-66", "sentence": ["TYPE", "STRAIGHT", "ISS", "PRICE", "100.92", "PAY", "DATE", "24.SEP.96"], "ner": [], "relations": []}
{"doc_key": "news-train-67", "sentence": ["FULL", "FEES", "1.875", "REOFFER", "99.32", "SPREAD", "+20", "BP"], "ner": [], "relations": []}
{"doc_key": "news-train-68", "sentence": ["MOODY", "AA1", "LISTING", "LUX", "PAY", "FREQ", "="], "ner": [], "relations": []}
{"doc_key": "news-train-69", "sentence": ["S&P", "=", "DENOMS", "(", "K", ")", "1-10-100", "SALE", "LIMITS", "US", "/", "UK", "/", "CA"], "ner": [[0, 0, "organisation"], [9, 9, "location"], [11, 11, "location"], [13, 13, "location"]], "relations": []}
{"doc_key": "news-train-70", "sentence": ["NEG", "PLG", "NO", "CRS", "DEFLT", "NO", "FORCE", "MAJ", "="], "ner": [], "relations": []}
{"doc_key": "news-train-71", "sentence": ["GOV", "LAW", "GERMAN", "HOME", "CTRY", "=", "TAX", "PROVS", "STANDARD"], "ner": [[2, 2, "misc"]], "relations": []}
{"doc_key": "news-train-72", "sentence": ["MGT", "/", "UND", "0.275", "SELL", "CONC", "1.60", "PRAECIP", "="], "ner": [], "relations": []}
{"doc_key": "news-train-73", "sentence": ["UNDERLYING", "GOVT", "BOND", "7.0", "PCT", "SEPT", "2001"], "ner": [], "relations": []}
{"doc_key": "news-train-74", "sentence": ["NOTES", "BAYERISCHE", "VEREINSBANK", "IS", "JOINT", "LEAD", "MANAGER"], "ner": [[1, 2, "organisation"]], "relations": []}
{"doc_key": "news-train-75", "sentence": ["--", "London", "Newsroom", "+44", "171", "542", "7658"], "ner": [[1, 2, "organisation"]], "relations": []}
{"doc_key": "news-train-76", "sentence": ["Venantius", "sets", "$", "300", "million", "January", "1999", "FRN", "."], "ner": [[0, 0, "organisation"]], "relations": []}
{"doc_key": "news-train-77", "sentence": ["LONDON", "1996-08-22"], "ner": [[0, 0, "location"]], "relations": []}
{"doc_key": "news-train-78", "sentence": ["The", "following", "floating-rate", "issue", "was", "announced", "by", "lead", "manager", "Lehman", "Brothers", "International", "."], "ner": [[9, 11, "organisation"]], "relations": []}
{"doc_key": "news-train-79", "sentence": ["BORROWER", "VENANTIUS", "AB", "(", "SWEDISH", "NATIONAL", "MORTGAGE", "AGENCY", ")"], "ner": [[1, 2, "organisation"], [4, 7, "misc"]], "relations": [[1, 2, 4, 7, "related-to", "borrows_from", true, false]]}
{"doc_key": "news-train-80", "sentence": ["AMT", "$", "300", "MLN", "SPREAD", "-", "12.5", "BP", "MATURITY", "21.JAN.99"], "ner": [], "relations": []}
{"doc_key": "news-train-81", "sentence": ["TYPE", "FRN", "BASE", "3M", "LIBOR", "PAY", "DATE", "S23.SEP.96"], "ner": [[3, 3, "organisation"]], "relations": []}
{"doc_key": "news-train-82", "sentence": ["LAST", "MOODY", "AA3", "ISS", "PRICE", "99.956", "FULL", "FEES", "10", "BP"], "ner": [], "relations": []}
{"doc_key": "news-train-83", "sentence": ["LAST", "S&P", "AA+", "REOFFER", "="], "ner": [[1, 1, "organisation"]], "relations": []}
{"doc_key": "news-train-84", "sentence": ["NOTES", "S", "SHORT", "FIRST", "COUPON"], "ner": [], "relations": []}
{"doc_key": "news-train-85", "sentence": ["LISTING", "LONDON", "DENOMS", "(", "K", ")", "1-10-100", "SALE", "LIMITS", "US", "/", "UK", "/", "JP", "/", "FR"], "ner": [[1, 1, "location"], [9, 9, "location"], [11, 11, "location"], [13, 13, "location"], [15, 15, "location"]], "relations": []}
{"doc_key": "news-train-86", "sentence": ["NEG", "PLG", "YES", "CRS", "DEFLT", "NO", "FORCE", "MAJ", "IPMA", "2"], "ner": [], "relations": []}
{"doc_key": "news-train-87", "sentence": ["GOV", "LAW", "ENGLISH", "HOME", "CTRY", "SWEDEN", "TAX", "PROVS", "STANDARD"], "ner": [[2, 4, "misc"], [5, 5, "location"]], "relations": []}
{"doc_key": "news-train-88", "sentence": ["MGT", "/", "UND", "5", "BP", "SELL", "CONC", "5", "BP", "PRAECIP", "="], "ner": [], "relations": []}
{"doc_key": "news-train-89", "sentence": ["NOTES", "ISSUED", "OFF", "EMTN", "PROGRAMME"], "ner": [], "relations": []}
{"doc_key": "news-train-90", "sentence": ["--", "London", "Newsroom", "+44", "171", "542", "8863"], "ner": [[1, 2, "organisation"]], "relations": []}
{"doc_key": "news-train-91", "sentence": ["Port", "conditions", "update", "-", "Syria", "-", "Lloyds", "Shipping", "."], "ner": [[4, 4, "location"], [6, 7, "organisation"]], "relations": []}
{"doc_key": "news-train-92", "sentence": ["Port", "conditions", "from", "Lloyds", "Shipping", "Intelligence", "Service", "--"], "ner": [[3, 6, "organisation"]], "relations": []}
{"doc_key": "news-train-93", "sentence": ["LATTAKIA", ",", "Aug", "10", "-", "waiting", "time", "at", "Lattakia", "and", "Tartous", "presently", "24", "hours", "."], "ner": [[0, 0, "location"], [8, 8, "location"], [10, 10, "location"]], "relations": [[0, 0, 8, 8, "named", "same", false, false]]}
{"doc_key": "news-train-94", "sentence": ["Israel", "plays", "down", "fears", "of", "war", "with", "Syria", "."], "ner": [[0, 0, "location"], [7, 7, "location"]], "relations": [[0, 0, 7, 7, "opposite", "potential_war", false, false]]}
{"doc_key": "news-train-95", "sentence": ["Colleen", "Siegel"], "ner": [[0, 1, "person"]], "relations": []}
{"doc_key": "news-train-96", "sentence": ["JERUSALEM", "1996-08-22"], "ner": [[0, 0, "location"]], "relations": []}
{"doc_key": "news-train-97", "sentence": ["Israel", "'s", "outgoing", "peace", "negotiator", "with", "Syria", "said", "on", "Thursday", "current", "tensions", "between", "the", "two", "countries", "appeared", "to", "be", "a", "storm", "in", "a", "teacup", "."], "ner": [[0, 0, "location"], [6, 6, "location"]], "relations": [[0, 0, 6, 6, "opposite", "tensions", false, false]]}
{"doc_key": "news-train-98", "sentence": ["Itamar", "Rabinovich", ",", "who", "as", "Israel", "'s", "ambassador", "to", "Washington", "conducted", "unfruitful", "negotiations", "with", "Syria", ",", "told", "Israel", "Radio", "it", "looked", "like", "Damascus", "wanted", "to", "talk", "rather", "than", "fight", "."], "ner": [[0, 1, "person"], [5, 5, "location"], [9, 9, "location"], [14, 14, "location"], [17, 18, "organisation"], [22, 22, "location"]], "relations": [[0, 1, 5, 5, "role", "ambassador_for", false, false], [0, 1, 9, 9, "role", "ambassador_to", false, false], [0, 1, 9, 9, "role", "negotiates_with", false, false], [0, 1, 17, 18, "related-to", "relays_information_to", false, false]]}
{"doc_key": "news-train-99", "sentence": ["\"", "It", "appears", "to", "me", "the", "{(1)[MISC]", "Syrian", "priority}", "is", "still", "to", "negotiate", "."], "ner": [], "relations": []}
{"doc_key": "news-train-100", "sentence": ["The", "Syrians", "are", "confused", ",", "they", "are", "definitely", "tense", ",", "but", "the", "general", "assessment", "here", "in", "Washington", "is", "that", "this", "is", "essentially", "a", "storm", "in", "a", "teacup", ",", "\"", "he", "said", "."], "ner": [[1, 1, "misc"], [16, 16, "location"]], "relations": []}
{"doc_key": "news-train-101", "sentence": ["Rabinovich", "is", "winding", "up", "his", "term", "as", "ambassador", "."], "ner": [[0, 0, "person"]], "relations": []}
{"doc_key": "news-train-102", "sentence": ["He", "will", "be", "replaced", "by", "Eliahu", "Ben-Elissar", ",", "a", "former", "Israeli", "envoy", "to", "Egypt", "and", "right-wing", "Likud", "party", "politician", "."], "ner": [[5, 6, "person"], [10, 11, "misc"], [13, 13, "location"], [16, 16, "organisation"]], "relations": [[5, 6, 13, 13, "role", "former_envoy", false, false], [5, 6, 16, 16, "role", "in_party", false, false], [10, 11, 5, 6, "named", "", false, false]]}
{"doc_key": "news-train-103", "sentence": ["Israel", "on", "Wednesday", "sent", "Syria", "a", "message", ",", "via", "Washington", ",", "saying", "it", "was", "committed", "to", "peace", "and", "wanted", "to", "open", "negotiations", "without", "preconditions", "."], "ner": [[0, 0, "location"], [4, 4, "location"], [9, 9, "location"]], "relations": [[0, 0, 4, 4, "role", "", false, false], [9, 9, 0, 0, "role", "middleman", false, false], [9, 9, 4, 4, "role", "middleman", false, false]]}
{"doc_key": "news-train-104", "sentence": ["But", "it", "slammed", "Damascus", "for", "creating", "what", "it", "called", "a", "dangerous", "atmosphere", "."], "ner": [[3, 3, "location"]], "relations": []}
{"doc_key": "news-train-105", "sentence": ["Syria", "accused", "Israel", "on", "Wednesday", "of", "launching", "a", "hysterical", "campaign", "against", "it", "after", "Israeli", "television", "reported", "that", "Damascus", "had", "recently", "test", "fired", "a", "missile", "."], "ner": [[0, 0, "location"], [2, 2, "location"], [13, 14, "misc"], [17, 17, "location"]], "relations": [[0, 0, 2, 2, "opposite", "", false, false], [13, 14, 17, 17, "related-to", "report_on", false, false]]}
{"doc_key": "news-train-106", "sentence": ["It", "said", "its", "arms", "purchases", "were", "for", "defensive", "purposes", "."], "ner": [], "relations": []}
{"doc_key": "news-train-107", "sentence": ["\"", "The", "message", "that", "we", "sent", "to", "(", "Syrian", "President", "Hafez", "al-", ")", "Assad", "is", "that", "Israel", "is", "ready", "at", "any", "time", "without", "preconditions", "to", "enter", "peace", "negotiations", ",", "\"", "Israeli", "Foreign", "Minister", "David", "Levy", "told", "Israel", "Radio", "in", "an", "interview", "."], "ner": [[8, 9, "misc"], [10, 13, "person"], [16, 16, "location"], [30, 32, "misc"], [33, 34, "person"], [36, 37, "organisation"]], "relations": [[8, 9, 10, 13, "named", "", false, false], [30, 32, 33, 34, "named", "", false, false], [33, 34, 10, 13, "related-to", "sends_message_to", false, false], [33, 34, 16, 16, "role", "", false, false], [33, 34, 36, 37, "related-to", "relays_information_to", false, false]]}
{"doc_key": "news-train-108", "sentence": ["Tension", "has", "mounted", "since", "Israeli", "Prime", "Minister", "Benjamin", "Netanyahu", "took", "office", "in", "June", "vowing", "to", "retain", "the", "Golan", "Heights", "Israel", "captured", "from", "Syria", "in", "the", "1967", "Middle", "East", "war", "."], "ner": [[4, 6, "misc"], [7, 8, "person"], [17, 18, "location"], [19, 19, "country"], [22, 22, "location"], [26, 27, "location"]], "relations": [[4, 6, 7, 8, "named", "", false, false], [17, 18, 19, 19, "physical", "", false, false], [17, 18, 22, 22, "physical", "", false, false], [19, 19, 26, 27, "part-of", "", false, false], [19, 19, 26, 27, "physical", "", false, false], [22, 22, 26, 27, "part-of", "", false, false], [22, 22, 26, 27, "physical", "", false, false]]}
{"doc_key": "news-train-109", "sentence": ["Israeli-Syrian", "peace", "talks", "have", "been", "deadlocked", "over", "the", "Golan", "since", "1991", "despite", "the", "previous", "government", "'s", "willingness", "to", "make", "Golan", "concessions", "."], "ner": [[0, 0, "misc"], [8, 8, "location"], [19, 19, "location"]], "relations": [[0, 0, 8, 8, "topic", "", false, false], [8, 8, 19, 19, "named", "same", false, false]]}
{"doc_key": "news-train-110", "sentence": ["Peace", "talks", "between", "the", "two", "sides", "were", "last", "held", "in", "February", "."], "ner": [], "relations": []}
{"doc_key": "news-train-111", "sentence": ["\"", "The", "voices", "coming", "out", "of", "Damascus", "are", "bad", ",", "not", "good", "."], "ner": [], "relations": []}
{"doc_key": "news-train-112", "sentence": ["The", "media", "..."], "ner": [], "relations": []}
{"doc_key": "news-train-113", "sentence": ["are", "full", "of", "expressions", "and", "declarations", "that", "must", "be", "worrying", "..."], "ner": [], "relations": []}
{"doc_key": "news-train-114", "sentence": ["this", "artificial", "atmosphere", "is", "very", "dangerous", "because", "those", "who", "spread", "it", "could", "become", "its", "prisoners", ",", "\"", "Levy", "said", "."], "ner": [[17, 17, "person"]], "relations": []}
{"doc_key": "news-train-115", "sentence": ["\"", "We", "expect", "from", "Syria", ",", "if", "its", "face", "is", "to", "peace", ",", "that", "it", "will", "answer", "Israel", "'s", "message", "to", "enter", "peace", "negotiations", "because", "that", "is", "our", "goal", ",", "\"", "he", "said", ".", "\""], "ner": [[4, 4, "location"], [17, 17, "location"]], "relations": [[4, 4, 17, 17, "related-to", "interact", false, false]]}
{"doc_key": "news-train-116", "sentence": ["We", "do", "not", "want", "a", "war", ",", "God", "forbid", "."], "ner": [[7, 7, "person"]], "relations": []}
{"doc_key": "news-train-117", "sentence": ["No", "one", "benefits", "from", "wars", ".", "\""], "ner": [], "relations": []}
{"doc_key": "news-train-118", "sentence": ["Israel", "'s", "Channel", "Two", "television", "said", "Damascus", "had", "sent", "a", "\"", "calming", "signal", "\"", "to", "Israel", "."], "ner": [[0, 0, "location"], [2, 3, "organisation"], [6, 6, "location"], [15, 15, "location"]], "relations": [[0, 0, 15, 15, "named", "same", false, false], [2, 3, 0, 0, "related-to", "", false, false], [6, 6, 15, 15, "related-to", "interact", false, false]]}
{"doc_key": "news-train-119", "sentence": ["It", "gave", "no", "source", "for", "the", "report", "."], "ner": [], "relations": []}
{"doc_key": "news-train-120", "sentence": ["Netanyahu", "and", "Levy", "'s", "spokesmen", "said", "they", "could", "not", "confirm", "it", "."], "ner": [[0, 0, "person"], [2, 2, "person"]], "relations": []}
{"doc_key": "news-train-121", "sentence": ["The", "television", "also", "said", "that", "Netanyahu", "had", "sent", "messages", "to", "reassure", "Syria", "via", "Cairo", ",", "the", "United", "States", "and", "Moscow", "."], "ner": [[5, 5, "person"], [11, 11, "location"], [13, 13, "location"], [16, 17, "location"], [19, 19, "location"]], "relations": [[5, 5, 11, 11, "role", "send_message_to", false, false], [13, 13, 5, 5, "role", "middleman", false, false], [13, 13, 11, 11, "role", "middleman", false, false], [16, 17, 5, 5, "role", "middleman", false, false], [16, 17, 11, 11, "role", "middleman", false, false], [19, 19, 5, 5, "role", "middleman", false, false], [19, 19, 11, 11, "role", "middleman", false, false]]}
{"doc_key": "news-train-122", "sentence": ["Polish", "diplomat", "denies", "nurses", "stranded", "in", "Libya", "."], "ner": [[0, 1, "misc"], [6, 6, "location"]], "relations": []}
{"doc_key": "news-train-123", "sentence": ["TUNIS", "1996-08-22"], "ner": [[0, 0, "location"]], "relations": []}
{"doc_key": "news-train-124", "sentence": ["A", "Polish", "diplomat", "on", "Thursday", "denied", "a", "Polish", "tabloid", "report", "this", "week", "that", "Libya", "was", "refusing", "exit", "visas", "to", "100", "Polish", "nurses", "trying", "to", "return", "home", "after", "working", "in", "the", "North", "African", "country", "."], "ner": [[1, 2, "misc"], [7, 9, "misc"], [13, 13, "location"], [20, 21, "misc"], [30, 32, "misc"]], "relations": [[1, 2, 7, 9, "opposite", "denies", false, false], [13, 13, 30, 32, "type-of", "", false, false], [20, 21, 13, 13, "physical", "", false, false]]}
{"doc_key": "news-train-125", "sentence": ["\"", "This", "is", "not", "true", "."], "ner": [], "relations": []}
{"doc_key": "news-train-126", "sentence": ["Up", "to", "today", ",", "we", "have", "no", "knowledge", "of", "any", "nurse", "stranded", "or", "kept", "in", "Libya", "without", "her", "will", ",", "and", "we", "have", "not", "received", "any", "complaint", ",", "\"", "the", "Polish", "embassy", "'s", "charge", "d'affaires", "in", "Tripoli", ",", "Tadeusz", "Awdankiewicz", ",", "told", "Reuters", "by", "telephone", "."], "ner": [[15, 15, "location"], [30, 31, "misc"], [36, 36, "location"], [38, 39, "person"], [42, 42, "organisation"]], "relations": [[38, 39, 30, 31, "role", "", false, false], [38, 39, 36, 36, "physical", "", false, false], [38, 39, 42, 42, "related-to", "", false, false]]}
{"doc_key": "news-train-127", "sentence": ["Poland", "'s", "labour", "ministry", "said", "this", "week", "it", "would", "send", "a", "team", "to", "Libya", "to", "investigate", ",", "but", "Awdankiewicz", "said", "the", "probe", "was", "prompted", "by", "some", "nurses", "complaining", "about", "their", "work", "conditions", "such", "as", "non-payment", "of", "their", "salaries", "."], "ner": [[0, 0, "location"], [13, 13, "location"], [18, 18, "person"]], "relations": []}
{"doc_key": "news-train-128", "sentence": ["He", "said", "that", "there", "are", "an", "estimated", "800", "Polish", "nurses", "working", "in", "Libya", "."], "ner": [[8, 9, "misc"], [12, 12, "location"]], "relations": [[8, 9, 12, 12, "physical", "", false, false]]}
{"doc_key": "news-train-129", "sentence": ["Two", "Iranian", "opposition", "leaders", "meet", "in", "Baghdad", "."], "ner": [[1, 3, "misc"], [6, 6, "location"]], "relations": [[1, 3, 6, 6, "physical", "", false, false]]}
{"doc_key": "news-train-130", "sentence": ["Hassan", "Hafidh"], "ner": [[0, 1, "person"]], "relations": []}
{"doc_key": "news-train-131", "sentence": ["BAGHDAD", "1996-08-22"], "ner": [[0, 0, "location"]], "relations": []}
{"doc_key": "news-train-132", "sentence": ["An", "Iranian", "exile", "group", "based", "in", "Iraq", "vowed", "on", "Thursday", "to", "extend", "support", "to", "Iran", "'s", "Kurdish", "rebels", "after", "they", "were", "attacked", "by", "Iranian", "troops", "deep", "inside", "Iraq", "last", "month", "."], "ner": [[1, 3, "misc"], [6, 6, "location"], [14, 14, "location"], [16, 17, "misc"], [23, 24, "misc"], [27, 27, "location"]], "relations": [[1, 3, 6, 6, "physical", "", false, false], [1, 3, 16, 17, "role", "supports", false, false], [6, 6, 27, 27, "named", "same", false, false], [16, 17, 14, 14, "physical", "", false, false], [16, 17, 23, 24, "opposite", "attacked_by", false, false], [16, 17, 27, 27, "physical", "", false, false]]}
{"doc_key": "news-train-133", "sentence": ["A", "Mujahideen", "Khalq", "statement", "said", "its", "leader", "Massoud", "Rajavi", "met", "in", "Baghdad", "the", "Secretary-General", "of", "the", "Kurdistan", "Democratic", "Party", "of", "Iran", "(", "KDPI", ")", "Hassan", "Rastegar", "on", "Wednesday", "and", "voiced", "his", "support", "to", "Iran", "'s", "rebel", "Kurds", "."], "ner": [[1, 2, "organisation"], [7, 8, "person"], [11, 11, "location"], [16, 20, "organisation"], [22, 22, "organisation"], [24, 25, "person"], [33, 33, "location"], [36, 36, "misc"]], "relations": [[7, 8, 1, 2, "role", "", false, false], [7, 8, 11, 11, "physical", "", false, false], [7, 8, 24, 25, "role", "meet", false, false], [7, 8, 36, 36, "role", "supports", false, false], [22, 22, 16, 20, "role", "", false, false], [24, 25, 11, 11, "physical", "", true, false], [24, 25, 16, 20, "role", "", false, false], [36, 36, 33, 33, "physical", "", false, false]]}
{"doc_key": "news-train-134", "sentence": ["\"", "Rajavi", "emphasised", "that", "the", "Iranian", "Resistance", "would", "continue", "to", "stand", "side", "by", "side", "with", "their", "Kurdish", "compatriots", "and", "the", "resistance", "movement", "in", "Iranian", "Kurdistan", ",", "\"", "it", "said", "."], "ner": [[1, 1, "misc"], [5, 6, "organisation"], [16, 17, "misc"], [23, 24, "location"]], "relations": [[5, 6, 16, 17, "role", "support", false, false], [5, 6, 23, 24, "physical", "", false, false], [16, 17, 23, 24, "physical", "", false, false]]}
{"doc_key": "news-train-135", "sentence": ["A", "spokesman", "for", "the", "group", "said", "the", "meeting", "\"", "signals", "a", "new", "level", "of", "cooperation", "between", "Mujahideen", "Khalq", "and", "the", "Iranian", "Kurdish", "oppositions", "\"", "."], "ner": [[16, 17, "organisation"], [20, 22, "misc"]], "relations": [[16, 17, 20, 22, "role", "coalition", false, false]]}
{"doc_key": "news-train-136", "sentence": ["Iran", "heavily", "bombarded", "targets", "in", "northern", "Iraq", "in", "July", "in", "pursuit", "of", "KDPI", "guerrillas", "based", "in", "Iraqi", "Kurdish", "areas", "outside", "the", "control", "of", "the", "government", "in", "Baghdad", "."], "ner": [[0, 0, "location"], [6, 6, "location"], [12, 12, "organisation"], [16, 18, "misc"], [26, 26, "location"]], "relations": [[0, 0, 6, 6, "opposite", "bombs", false, false], [0, 0, 12, 12, "opposite", "", false, false], [12, 12, 16, 18, "physical", "", false, false], [16, 18, 6, 6, "physical", "", false, false]]}
{"doc_key": "news-train-137", "sentence": ["Iraqi", "Kurdish", "areas", "bordering", "Iran", "are", "under", "the", "control", "of", "guerrillas", "of", "the", "Iraqi", "Kurdish", "Patriotic", "Union", "of", "Kurdistan", "(", "PUK", ")", "group", "."], "ner": [[0, 2, "location"], [4, 4, "location"], [13, 18, "organisation"], [20, 20, "organisation"]], "relations": [[0, 2, 4, 4, "physical", "", false, false], [13, 18, 0, 2, "physical", "", false, false], [20, 20, 13, 18, "named", "", false, false]]}
{"doc_key": "news-train-138", "sentence": ["PUK", "and", "Iraq", "'s", "Kurdistan", "Democratic", "Party", "(", "KDP", ")", "the", "two", "main", "Iraqi", "Kurdish", "factions", ",", "have", "had", "northern", "Iraq", "under", "their", "control", "since", "Iraqi", "forces", "were", "ousted", "from", "Kuwait", "in", "the", "1991", "Gulf", "War", "."], "ner": [[0, 0, "organisation"], [2, 2, "location"], [4, 6, "organisation"], [8, 8, "organisation"], [13, 15, "misc"], [20, 20, "location"], [25, 26, "misc"], [30, 30, "location"], [34, 35, "misc"]], "relations": [[0, 0, 13, 15, "type-of", "", false, false], [0, 0, 20, 20, "physical", "", false, false], [4, 6, 2, 2, "physical", "", false, false], [4, 6, 13, 15, "type-of", "", false, false], [4, 6, 20, 20, "part-of", "", false, false], [8, 8, 4, 6, "named", "", false, false], [25, 26, 30, 30, "part-of", "", false, false], [25, 26, 34, 35, "temporal", "", false, false]]}
{"doc_key": "news-train-139", "sentence": ["Clashes", "between", "the", "two", "parties", "broke", "out", "at", "the", "weekend", "in", "the", "most", "serious", "fighting", "since", "a", "U.S.-sponsored", "ceasefire", "last", "year", "."], "ner": [[17, 18, "misc"]], "relations": []}
{"doc_key": "news-train-140", "sentence": ["Mujahideen", "Khalq", "said", "Iranian", "troops", "had", "also", "been", "shelling", "KDP", "positions", "in", "Qasri", "region", "in", "Suleimaniya", "province", "near", "the", "Iranian", "border", "over", "the", "last", "two", "days", "."], "ner": [[0, 1, "organisation"], [3, 4, "misc"], [9, 9, "organisation"], [12, 12, "location"], [15, 15, "location"], [19, 20, "misc"]], "relations": [[3, 4, 9, 9, "opposite", "bombs", false, false], [9, 9, 12, 12, "physical", "", false, false], [12, 12, 15, 15, "physical", "", false, false], [15, 15, 19, 20, "physical", "", false, false]]}
{"doc_key": "news-train-141", "sentence": ["It", "said", "about", "100", "Iraqi", "Kurds", "were", "killed", "or", "wounded", "in", "the", "attack", "."], "ner": [[4, 5, "misc"]], "relations": []}
{"doc_key": "news-train-142", "sentence": ["Both", "Iran", "and", "Turkey", "mount", "air", "and", "land", "strikes", "at", "targets", "in", "northern", "Iraq", "in", "pursuit", "of", "their", "own", "Kurdish", "rebels", "."], "ner": [[1, 1, "location"], [3, 3, "location"], [13, 13, "location"], [19, 20, "misc"]], "relations": [[1, 1, 19, 20, "opposite", "", false, false], [3, 3, 19, 20, "opposite", "", false, false], [19, 20, 13, 13, "physical", "", false, false]]}
{"doc_key": "news-train-143", "sentence": ["A", "U.S.-led", "air", "force", "in", "southern", "Turkey", "protects", "Iraqi", "Kurds", "from", "possible", "attacks", "by", "Baghdad", "troops", "."], "ner": [[1, 3, "misc"], [6, 6, "country"], [8, 9, "misc"], [14, 14, "location"]], "relations": [[1, 3, 6, 6, "physical", "", false, false], [1, 3, 8, 9, "role", "protects", false, false], [8, 9, 14, 14, "opposite", "", false, false]]}
{"doc_key": "news-train-144", "sentence": ["Saudi", "riyal", "rates", "steady", "in", "quiet", "summer", "trade", "."], "ner": [[0, 0, "misc"]], "relations": []}
{"doc_key": "news-train-145", "sentence": ["MANAMA", "1996-08-22"], "ner": [[0, 0, "location"]], "relations": []}
{"doc_key": "news-train-146", "sentence": ["The", "spot", "Saudi", "riyal", "against", "the", "dollar", "and", "riyal", "interbank", "deposit", "rates", "were", "mainly", "steady", "this", "week", "in", "quiet", "summer", "trade", ",", "dealers", "in", "the", "kingdom", "said", "."], "ner": [[2, 3, "misc"]], "relations": []}
{"doc_key": "news-train-147", "sentence": ["\"", "There", "were", "no", "changes", "in", "Saudi", "riyal", "rates", "."], "ner": [], "relations": []}
{"doc_key": "news-train-148", "sentence": ["The", "market", "was", "very", "quiet", "because", "of", "summer", "holidays", ",", "\"", "one", "dealer", "said", "."], "ner": [], "relations": []}
{"doc_key": "news-train-149", "sentence": ["The", "spot", "riyal", "was", "put", "at", "3.7504", "/", "06", "to", "the", "dollar", "."], "ner": [], "relations": []}
{"doc_key": "news-train-150", "sentence": ["One-month", "interbank", "deposits", "were", "at", "5-1/2", ",", "3/8", "percent", ",", "three", "months", "were", "5-5/8", ",", "1/2", "percent", "and", "six", "months", "were", "5-3/4", ",", "5/8", "percent", "."], "ner": [[0, 0, "misc"]], "relations": []}
{"doc_key": "news-train-151", "sentence": ["One-year", "funds", "were", "at", "six", ",", "5-7/8", "percent", "."], "ner": [[0, 0, "misc"]], "relations": []}
{"doc_key": "news-train-152", "sentence": ["Israel", "approves", "Arafat", "'s", "flight", "to", "West", "Bank", "."], "ner": [[0, 0, "location"], [2, 2, "person"], [6, 7, "location"]], "relations": [[0, 0, 2, 2, "related-to", "approves_of", false, false], [2, 2, 6, 7, "physical", "", false, false]]}
{"doc_key": "news-train-153", "sentence": ["JERUSALEM", "1996-08-22"], "ner": [[0, 0, "location"]], "relations": []}
{"doc_key": "news-train-154", "sentence": ["Israel", "gave", "Palestinian", "President", "Yasser", "Arafat", "permission", "on", "Thursday", "to", "fly", "over", "its", "territory", "to", "the", "West", "Bank", ",", "ending", "a", "brief", "Israeli-PLO", "crisis", ",", "an", "Arafat", "adviser", "said", "."], "ner": [[0, 0, "location"], [2, 3, "misc"], [4, 5, "person"], [16, 17, "location"], [22, 23, "misc"], [26, 26, "person"]], "relations": [[0, 0, 4, 5, "role", "give_permission_to", false, false], [2, 3, 4, 5, "named", "", false, false], [4, 5, 16, 17, "physical", "", false, false], [4, 5, 26, 26, "named", "same", false, false]]}
{"doc_key": "news-train-155", "sentence": ["\"", "The", "problem", "is", "over", "."], "ner": [], "relations": []}
{"doc_key": "news-train-156", "sentence": ["The", "president", "'s", "aircraft", "has", "received", "permission", "to", "pass", "through", "Israeli", "airspace", "but", "the", "president", "is", "not", "expected", "to", "travel", "to", "the", "West", "Bank", "before", "Monday", ",", "\"", "Nabil", "Abu", "Rdainah", "told", "Reuters", "."], "ner": [[10, 11, "misc"], [22, 23, "location"], [28, 30, "person"], [32, 32, "organisation"]], "relations": [[28, 30, 32, 32, "related-to", "", false, false]]}
{"doc_key": "news-train-157", "sentence": ["Arafat", "had", "been", "scheduled", "to", "meet", "former", "Israeli", "prime", "minister", "Shimon", "Peres", "in", "the", "West", "Bank", "town", "of", "Ramallah", "on", "Thursday", "but", "the", "venue", "was", "changed", "to", "Gaza", "after", "Israel", "denied", "flight", "clearance", "to", "the", "Palestinian", "leader", "'s", "helicopters", "."], "ner": [[0, 0, "person"], [7, 9, "misc"], [10, 11, "person"], [14, 15, "location"], [18, 18, "location"], [27, 27, "location"], [29, 29, "location"], [35, 36, "misc"]], "relations": [[0, 0, 10, 11, "related-to", "meet_with", false, false], [0, 0, 18, 18, "physical", "", false, false], [0, 0, 27, 27, "physical", "", false, false], [7, 9, 10, 11, "named", "", false, false], [10, 11, 18, 18, "physical", "", false, false], [10, 11, 27, 27, "physical", "", false, false], [18, 18, 14, 15, "physical", "", false, false], [29, 29, 0, 0, "opposite", "denies_clearance", false, false], [35, 36, 0, 0, "named", "", false, false]]}
{"doc_key": "news-train-158", "sentence": ["Palestinian", "officials", "accused", "right-wing", "Prime", "Minister", "Benjamin", "Netanyahu", "of", "trying", "to", "stop", "the", "Ramallah", "meeting", "by", "keeping", "Arafat", "grounded", "."], "ner": [[0, 1, "misc"], [6, 7, "person"], [13, 13, "location"], [17, 17, "person"]], "relations": [[0, 1, 6, 7, "opposite", "", false, false], [6, 7, 17, 17, "opposite", "", false, false]]}
{"doc_key": "news-train-159", "sentence": ["Arafat", "subsequently", "cancelled", "a", "meeting", "between", "Israeli", "and", "PLO", "officials", ",", "on", "civilian", "affairs", ",", "at", "the", "Allenby", "Bridge", "crossing", "between", "Jordan", "and", "the", "West", "Bank", "."], "ner": [[0, 0, "person"], [6, 6, "misc"], [8, 8, "organisation"], [17, 18, "location"], [21, 21, "location"], [24, 25, "location"]], "relations": [[0, 0, 8, 8, "role", "", false, false], [6, 6, 8, 8, "opposite", "", false, false], [17, 18, 21, 21, "physical", "", false, false], [17, 18, 24, 25, "physical", "", false, false]]}
{"doc_key": "news-train-160", "sentence": ["Abu", "Rdainah", "said", "Arafat", "had", "decided", "against", "flying", "to", "the", "West", "Bank", "on", "Thursday", ",", "after", "Israel", "lifted", "the", "ban", ",", "because", "he", "had", "a", "busy", "schedule", "in", "Gaza", "and", "would", "not", "be", "free", "until", "Monday", "."], "ner": [[0, 1, "person"], [3, 3, "person"], [10, 11, "location"], [16, 16, "location"], [28, 28, "location"]], "relations": [[3, 3, 10, 11, "physical", "not_go_to", false, false], [3, 3, 28, 28, "physical", "", false, false]]}
{"doc_key": "news-train-161", "sentence": ["Arafat", "to", "meet", "Peres", "in", "Gaza", "after", "flight", "ban", "."], "ner": [[0, 0, "person"], [3, 3, "person"], [5, 5, "location"]], "relations": [[0, 0, 3, 3, "social", "", false, false], [0, 0, 5, 5, "physical", "", false, false], [3, 3, 5, 5, "physical", "", false, false]]}
{"doc_key": "news-train-162", "sentence": ["JERUSALEM", "1996-08-22"], "ner": [[0, 0, "location"]], "relations": []}
{"doc_key": "news-train-163", "sentence": ["Yasser", "Arafat", "will", "meet", "Shimon", "Peres", "in", "Gaza", "on", "Thursday", "after", "Palestinians", "said", "the", "right-wing", "Israeli", "government", "had", "barred", "the", "Palestinian", "leader", "from", "flying", "to", "the", "West", "Bank", "for", "talks", "with", "the", "former", "prime", "minister", "."], "ner": [[0, 1, "person"], [4, 5, "person"], [7, 7, "location"], [11, 11, "misc"], [15, 16, "misc"], [20, 21, "misc"], [26, 27, "location"]], "relations": [[0, 1, 4, 5, "social", "meet", false, false], [0, 1, 7, 7, "physical", "", false, false], [4, 5, 7, 7, "physical", "", false, false]]}
{"doc_key": "news-train-164", "sentence": ["Japan", "'s", "Finance", "Minister", "Wataru", "Kubo", "told", "a", "news", "conference", "on", "Wednesday", "that", "he", "believes", "that", "the", "Bank", "of", "Japan", "'s", "(", "BOJ", ")", "interest", "rate", "policy", "which", "is", "geared", "towards", "ensuring", "economic", "growth", "has", "not", "changed", "after", "the", "release", "of", "the", "central", "bank", "'s", "\"", "tankan", "\"", "survey", "."], "ner": [[0, 0, "location"], [4, 5, "person"], [17, 19, "organisation"], [22, 22, "organisation"]], "relations": [[4, 5, 0, 0, "role", "", false, false], [22, 22, 17, 19, "named", "", false, false]]}
